{"ProjectBreakpoints":"{\"Value\":{},\"CodeBreakpoints\":{}}","Compiler":"2","ProjectWatches":"{\"Value\":[]}","OpenedDocuments":"[{\"DocumentPath\":\"ITA_RPA_Main.xaml\",\"FactoryId\":\"{ACB8E7BA-F093-44C1-9B50-33ECA51AAE16}\"}]","ProjectActivitiesViewState":"{\"Proceso/00 - Comun/ITA_RPA_Envio_Correos.xaml\":[{\"ActivityIdRef\":\"SendMailConnections_1\",\"IsAdvancedOptionsExpanded\":false,\"Categories\":{\"Recipients\":true,\"Options\":true},\"Widgets\":{}},{\"ActivityIdRef\":\"LogMessage_1\",\"IsAdvancedOptionsExpanded\":false,\"Widgets\":{}}],\"ITA_RPA_Main.xaml\":[{\"ActivityIdRef\":\"InvokeWorkflowFile_5\",\"IsAdvancedOptionsExpanded\":false,\"Categories\":{\"Common\":true,\"Options\":true,\"Log\":true},\"Widgets\":{}},{\"ActivityIdRef\":\"InvokeWorkflowFile_1\",\"IsAdvancedOptionsExpanded\":false,\"Categories\":{\"Common\":true,\"Options\":true,\"Log\":true,\"Output\":true},\"Widgets\":{}},{\"ActivityIdRef\":\"InvokeWorkflowFile_10\",\"IsAdvancedOptionsExpanded\":false,\"Categories\":{\"Common\":true,\"Options\":true,\"Log\":true},\"Widgets\":{}},{\"ActivityIdRef\":\"If_1\",\"IsAdvancedOptionsExpanded\":false,\"Widgets\":{\"Then\":{\"ShowExpanded\":true},\"Else\":{\"ShowExpanded\":true}}},{\"ActivityIdRef\":\"If_2\",\"IsAdvancedOptionsExpanded\":false,\"Widgets\":{\"Then\":{\"ShowExpanded\":true},\"Else\":{\"ShowExpanded\":true}}},{\"ActivityIdRef\":\"If_3\",\"IsAdvancedOptionsExpanded\":false,\"Widgets\":{}},{\"ActivityIdRef\":\"InvokeWorkflowFile_11\",\"IsAdvancedOptionsExpanded\":false,\"Categories\":{\"Common\":true,\"Options\":true,\"Log\":true},\"Widgets\":{}},{\"ActivityIdRef\":\"InvokeWorkflowFile_7\",\"IsAdvancedOptionsExpanded\":false,\"Categories\":{\"Common\":true,\"Options\":true,\"Log\":true},\"Widgets\":{}},{\"ActivityIdRef\":\"InvokeWorkflowFile_12\",\"IsAdvancedOptionsExpanded\":false,\"Categories\":{\"Common\":true,\"Options\":true,\"Log\":true},\"Widgets\":{}},{\"ActivityIdRef\":\"InvokeWorkflowFile_8\",\"IsAdvancedOptionsExpanded\":false,\"Categories\":{\"Common\":true,\"Options\":true,\"Log\":true},\"Widgets\":{}},{\"ActivityIdRef\":\"InvokeWorkflowFile_13\",\"IsAdvancedOptionsExpanded\":false,\"Categories\":{\"Common\":true,\"Options\":true,\"Log\":true},\"Widgets\":{}},{\"ActivityIdRef\":\"InvokeWorkflowFile_9\",\"IsAdvancedOptionsExpanded\":false,\"Categories\":{\"Common\":true,\"Options\":true,\"Log\":true},\"Widgets\":{}},{\"ActivityIdRef\":\"InvokeWorkflowFile_14\",\"IsAdvancedOptionsExpanded\":false,\"Categories\":{\"Common\":true,\"Options\":true,\"Log\":true},\"Widgets\":{}},{\"ActivityIdRef\":\"InvokeWorkflowFile_6\",\"IsAdvancedOptionsExpanded\":false,\"Categories\":{\"Common\":true,\"Options\":true,\"Log\":true},\"Widgets\":{}},{\"ActivityIdRef\":\"If_4\",\"IsAdvancedOptionsExpanded\":false,\"Widgets\":{\"Then\":{\"ShowExpanded\":true},\"Else\":{\"ShowExpanded\":true}}},{\"ActivityIdRef\":\"InvokeWorkflowFile_15\",\"IsAdvancedOptionsExpanded\":false,\"Categories\":{\"Common\":true,\"Options\":true,\"Log\":true},\"Widgets\":{}},{\"ActivityIdRef\":\"InvokeWorkflowFile_16\",\"IsAdvancedOptionsExpanded\":false,\"Categories\":{\"Common\":true,\"Options\":true,\"Log\":true},\"Widgets\":{}},{\"ActivityIdRef\":\"InvokeWorkflowFile_2\",\"IsAdvancedOptionsExpanded\":false,\"Categories\":{\"Common\":true,\"Options\":true,\"Log\":true},\"Widgets\":{}},{\"ActivityIdRef\":\"InvokeWorkflowFile_3\",\"IsAdvancedOptionsExpanded\":false,\"Categories\":{\"Common\":true,\"Options\":true,\"Log\":true},\"Widgets\":{}},{\"ActivityIdRef\":\"InvokeWorkflowFile_4\",\"IsAdvancedOptionsExpanded\":false,\"Categories\":{\"Common\":true,\"Options\":true,\"Log\":true},\"Widgets\":{}},{\"ActivityIdRef\":\"If_5\",\"IsAdvancedOptionsExpanded\":false,\"Widgets\":{\"Then\":{\"ShowExpanded\":true},\"Else\":{\"ShowExpanded\":true}}},{\"ActivityIdRef\":\"InvokeWorkflowFile_17\",\"IsAdvancedOptionsExpanded\":false,\"Categories\":{\"Common\":true,\"Options\":true,\"Log\":true},\"Widgets\":{}},{\"ActivityIdRef\":\"InvokeWorkflowFile_18\",\"IsAdvancedOptionsExpanded\":false,\"Categories\":{\"Common\":true,\"Options\":true,\"Log\":true},\"Widgets\":{}}],\"Proceso/03 - Procesar Archivos Txt/ITA_RPA_Procesar_Archivos_Txt.xaml\":[{\"ActivityIdRef\":\"If_1\",\"IsAdvancedOptionsExpanded\":false,\"Widgets\":{\"Then\":{\"ShowExpanded\":true},\"Else\":{\"ShowExpanded\":true}}},{\"ActivityIdRef\":\"CopyFile_2\",\"IsAdvancedOptionsExpanded\":false,\"Categories\":{\"Options\":true},\"Widgets\":{}},{\"ActivityIdRef\":\"Delay_3\",\"IsAdvancedOptionsExpanded\":false,\"Widgets\":{}},{\"ActivityIdRef\":\"ReadTextFile_1\",\"IsAdvancedOptionsExpanded\":false,\"Categories\":{\"Common\":true,\"File\":true,\"Output\":true},\"Widgets\":{}},{\"ActivityIdRef\":\"InvokeWorkflowFile_15\",\"IsAdvancedOptionsExpanded\":false,\"Categories\":{\"Common\":true,\"Options\":true,\"Log\":true},\"Widgets\":{}},{\"ActivityIdRef\":\"InvokeWorkflowFile_17\",\"IsAdvancedOptionsExpanded\":false,\"Categories\":{\"Common\":true,\"Options\":true,\"Log\":true},\"Widgets\":{}},{\"ActivityIdRef\":\"InvokeWorkflowFile_18\",\"IsAdvancedOptionsExpanded\":false,\"Categories\":{\"Common\":true,\"Options\":true,\"Log\":true},\"Widgets\":{}},{\"ActivityIdRef\":\"InvokeWorkflowFile_19\",\"IsAdvancedOptionsExpanded\":false,\"Categories\":{\"Common\":true,\"Options\":true,\"Log\":true},\"Widgets\":{}},{\"ActivityIdRef\":\"InvokeWorkflowFile_20\",\"IsAdvancedOptionsExpanded\":false,\"Categories\":{\"Common\":true,\"Options\":true,\"Log\":true},\"Widgets\":{}},{\"ActivityIdRef\":\"InvokeWorkflowFile_21\",\"IsAdvancedOptionsExpanded\":false,\"Categories\":{\"Common\":true,\"Options\":true,\"Log\":true},\"Widgets\":{}},{\"ActivityIdRef\":\"InvokeWorkflowFile_4\",\"IsAdvancedOptionsExpanded\":false,\"Categories\":{\"Common\":true,\"Options\":true,\"Log\":true},\"Widgets\":{}},{\"ActivityIdRef\":\"CopyFile_4\",\"IsAdvancedOptionsExpanded\":false,\"Categories\":{\"Options\":true},\"Widgets\":{}},{\"ActivityIdRef\":\"InvokeWorkflowFile_22\",\"IsAdvancedOptionsExpanded\":false,\"Categories\":{\"Common\":true,\"Options\":true,\"Log\":true},\"Widgets\":{}},{\"ActivityIdRef\":\"InvokeWorkflowFile_1\",\"IsAdvancedOptionsExpanded\":false,\"Categories\":{\"Common\":true,\"Options\":true,\"Log\":true},\"Widgets\":{}},{\"ActivityIdRef\":\"InvokeWorkflowFile_3\",\"IsAdvancedOptionsExpanded\":false,\"Categories\":{\"Common\":true,\"Options\":true,\"Log\":true},\"Widgets\":{}},{\"ActivityIdRef\":\"If_3\",\"IsAdvancedOptionsExpanded\":false,\"Widgets\":{\"Then\":{\"ShowExpanded\":true},\"Else\":{\"ShowExpanded\":true}}},{\"ActivityIdRef\":\"InvokeWorkflowFile_26\",\"IsAdvancedOptionsExpanded\":false,\"Categories\":{\"Common\":true,\"Options\":true,\"Log\":true},\"Widgets\":{}},{\"ActivityIdRef\":\"CreateDirectory_2\",\"IsAdvancedOptionsExpanded\":false,\"Categories\":{\"Common\":true,\"Output\":true},\"Widgets\":{}},{\"ActivityIdRef\":\"CreateDirectory_1\",\"IsAdvancedOptionsExpanded\":false,\"Categories\":{\"Common\":true,\"Output\":true},\"Widgets\":{}},{\"ActivityIdRef\":\"InvokeWorkflowFile_13\",\"IsAdvancedOptionsExpanded\":false,\"Categories\":{\"Common\":true,\"Options\":true,\"Log\":true},\"Widgets\":{}},{\"ActivityIdRef\":\"If_4\",\"IsAdvancedOptionsExpanded\":false,\"Widgets\":{\"Then\":{\"ShowExpanded\":true},\"Else\":{\"ShowExpanded\":true}}}],\"Proceso/02 - Verificacion de Insumos/ITA_RPA_Verificacion_Carpetas.xaml\":[{\"ActivityIdRef\":\"LogMessage_1\",\"IsAdvancedOptionsExpanded\":false,\"Widgets\":{}},{\"ActivityIdRef\":\"If_1\",\"IsAdvancedOptionsExpanded\":false,\"Widgets\":{}},{\"ActivityIdRef\":\"LogMessage_3\",\"IsAdvancedOptionsExpanded\":false,\"Widgets\":{}},{\"ActivityIdRef\":\"If_2\",\"IsAdvancedOptionsExpanded\":false,\"Widgets\":{}},{\"ActivityIdRef\":\"LogMessage_4\",\"IsAdvancedOptionsExpanded\":false,\"Widgets\":{}},{\"ActivityIdRef\":\"If_3\",\"IsAdvancedOptionsExpanded\":false,\"Widgets\":{}},{\"ActivityIdRef\":\"LogMessage_5\",\"IsAdvancedOptionsExpanded\":false,\"Widgets\":{}},{\"ActivityIdRef\":\"If_4\",\"IsAdvancedOptionsExpanded\":false,\"Widgets\":{}},{\"ActivityIdRef\":\"LogMessage_6\",\"IsAdvancedOptionsExpanded\":false,\"Widgets\":{}},{\"ActivityIdRef\":\"If_5\",\"IsAdvancedOptionsExpanded\":false,\"Widgets\":{\"Then\":{\"ShowExpanded\":true},\"Else\":{\"ShowExpanded\":true}}},{\"ActivityIdRef\":\"LogMessage_7\",\"IsAdvancedOptionsExpanded\":false,\"Widgets\":{}},{\"ActivityIdRef\":\"LogMessage_2\",\"IsAdvancedOptionsExpanded\":false,\"Widgets\":{}},{\"ActivityIdRef\":\"CreateDirectory_7\",\"IsAdvancedOptionsExpanded\":false,\"Categories\":{\"Common\":true,\"Output\":true},\"Widgets\":{}},{\"ActivityIdRef\":\"If_6\",\"IsAdvancedOptionsExpanded\":false,\"Widgets\":{\"Then\":{\"ShowExpanded\":true},\"Else\":{\"ShowExpanded\":true}}},{\"ActivityIdRef\":\"LogMessage_8\",\"IsAdvancedOptionsExpanded\":false,\"Widgets\":{}},{\"ActivityIdRef\":\"If_7\",\"IsAdvancedOptionsExpanded\":false,\"Widgets\":{\"Then\":{\"ShowExpanded\":true},\"Else\":{\"ShowExpanded\":true}}},{\"ActivityIdRef\":\"LogMessage_9\",\"IsAdvancedOptionsExpanded\":false,\"Widgets\":{}},{\"ActivityIdRef\":\"CreateDirectory_8\",\"IsAdvancedOptionsExpanded\":false,\"Categories\":{\"Common\":true,\"Output\":true},\"Widgets\":{}},{\"ActivityIdRef\":\"CreateDirectory_9\",\"IsAdvancedOptionsExpanded\":false,\"Categories\":{\"Common\":true,\"Output\":true},\"Widgets\":{}}],\"Proceso/04 - Copia de Archivos Procesados/ITA_RPA_Copiar_Procesados_SharePoint.xaml\":[{\"ActivityIdRef\":\"InvokeWorkflowFile_1\",\"IsAdvancedOptionsExpanded\":false,\"Categories\":{\"Common\":true,\"Options\":true,\"Log\":true},\"Widgets\":{}},{\"ActivityIdRef\":\"InvokeWorkflowFile_2\",\"IsAdvancedOptionsExpanded\":false,\"Categories\":{\"Common\":true,\"Options\":true,\"Log\":true},\"Widgets\":{}},{\"ActivityIdRef\":\"CopyFolderX_1\",\"IsAdvancedOptionsExpanded\":false,\"Categories\":{\"Options\":true},\"Widgets\":{}},{\"ActivityIdRef\":\"LogMessage_1\",\"IsAdvancedOptionsExpanded\":false,\"Widgets\":{}},{\"ActivityIdRef\":\"If_1\",\"IsAdvancedOptionsExpanded\":false,\"Widgets\":{\"Then\":{\"ShowExpanded\":true},\"Else\":{\"ShowExpanded\":true}}},{\"ActivityIdRef\":\"CreateDirectory_1\",\"IsAdvancedOptionsExpanded\":false,\"Categories\":{\"Common\":true,\"Output\":true},\"Widgets\":{}},{\"ActivityIdRef\":\"Delay_1\",\"IsAdvancedOptionsExpanded\":false,\"Widgets\":{}}],\"Proceso/01 - Inicializacion/ITA_RPA_Lectura_Archivo_Configuracion.xaml\":[{\"ActivityIdRef\":\"LogMessage_1\",\"IsAdvancedOptionsExpanded\":false,\"Widgets\":{}},{\"ActivityIdRef\":\"GetRobotAsset_1\",\"IsAdvancedOptionsExpanded\":false,\"Categories\":{\"Misc\":true,\"Output\":true},\"Widgets\":{}},{\"ActivityIdRef\":\"ForEachRow_1\",\"IsAdvancedOptionsExpanded\":false,\"Categories\":{\"\":true},\"Widgets\":{\"Body\":{\"ShowExpanded\":true}}}],\"Proceso/00 - Comun/ITA_RPA_Logs.xaml\":[{\"ActivityIdRef\":\"LogMessage_2\",\"IsAdvancedOptionsExpanded\":false,\"Widgets\":{}},{\"ActivityIdRef\":\"LogMessage_4\",\"IsAdvancedOptionsExpanded\":false,\"Widgets\":{}},{\"ActivityIdRef\":\"LogMessage_5\",\"IsAdvancedOptionsExpanded\":false,\"Widgets\":{}}],\"Proceso/02 - Verificacion de Insumos/ITA_RPA_Verificacion_Archivos.xaml\":[{\"ActivityIdRef\":\"LogMessage_1\",\"IsAdvancedOptionsExpanded\":false,\"Widgets\":{}},{\"ActivityIdRef\":\"If_1\",\"IsAdvancedOptionsExpanded\":false,\"Widgets\":{\"Then\":{\"ShowExpanded\":true},\"Else\":{\"ShowExpanded\":true}}},{\"ActivityIdRef\":\"InvokeWorkflowFile_3\",\"IsAdvancedOptionsExpanded\":false,\"Categories\":{\"Common\":true,\"Options\":true,\"Log\":true},\"Widgets\":{}},{\"ActivityIdRef\":\"LogMessage_2\",\"IsAdvancedOptionsExpanded\":false,\"Widgets\":{}},{\"ActivityIdRef\":\"Throw_1\",\"IsAdvancedOptionsExpanded\":false,\"Widgets\":{}},{\"ActivityIdRef\":\"If_2\",\"IsAdvancedOptionsExpanded\":false,\"Widgets\":{\"Then\":{\"ShowExpanded\":true},\"Else\":{\"ShowExpanded\":true}}},{\"ActivityIdRef\":\"Throw_2\",\"IsAdvancedOptionsExpanded\":false,\"Widgets\":{}},{\"ActivityIdRef\":\"InvokeWorkflowFile_1\",\"IsAdvancedOptionsExpanded\":false,\"Categories\":{\"Common\":true,\"Options\":true,\"Log\":true},\"Widgets\":{}},{\"ActivityIdRef\":\"InvokeWorkflowFile_2\",\"IsAdvancedOptionsExpanded\":false,\"Categories\":{\"Common\":true,\"Options\":true,\"Log\":true},\"Widgets\":{}},{\"ActivityIdRef\":\"InvokeWorkflowFile_4\",\"IsAdvancedOptionsExpanded\":false,\"Categories\":{\"Common\":true,\"Options\":true,\"Log\":true},\"Widgets\":{}},{\"ActivityIdRef\":\"InvokeWorkflowFile_5\",\"IsAdvancedOptionsExpanded\":false,\"Categories\":{\"Common\":true,\"Options\":true,\"Log\":true},\"Widgets\":{}},{\"ActivityIdRef\":\"InvokeWorkflowFile_6\",\"IsAdvancedOptionsExpanded\":false,\"Categories\":{\"Common\":true,\"Options\":true,\"Log\":true},\"Widgets\":{}},{\"ActivityIdRef\":\"InvokeWorkflowFile_7\",\"IsAdvancedOptionsExpanded\":false,\"Categories\":{\"Common\":true,\"Options\":true,\"Log\":true},\"Widgets\":{}}]}","ProjectSettings":"{\"IncludeSourcesByDefault\":true,\"RemoveUnusedDependencies\":false}"}